setup.py
api_iam_helpers/__init__.py
api_iam_helpers/build_req.py
api_iam_helpers.egg-info/PKG-INFO
api_iam_helpers.egg-info/SOURCES.txt
api_iam_helpers.egg-info/dependency_links.txt
api_iam_helpers.egg-info/not-zip-safe
api_iam_helpers.egg-info/top_level.txt