Metadata-Version: 1.0
Name: api-iam-helpers
Version: 0.1
Summary: Utilities for building IAM authenticated API requests
Home-page: https://github.com/georgebuckerfield/api-iam-helpers
Author: George Buckerfield
Author-email: george.buckerfield@cancer.org.uk
License: MIT
Platform: UNKNOWN
